mini_coffee/__init__.py
mini_coffee/core/state.py
mini_coffee/core/workflow.py
mini_coffee/gui/operator/__init__.py
mini_coffee/gui/operator/app.py
mini_coffee/gui/operator/calibration.py
mini_coffee/gui/operator/config/calibration/calibration.json
mini_coffee/gui/operator/config/calibration/components.json
mini_coffee/gui/operator/config/calibration/nodes.json
mini_coffee/gui/operator/settings.py
mini_coffee/gui/operator/status_check.py
mini_coffee/hardware/arm/controller.py
mini_coffee/hardware/arm/xarm/__init__.py
mini_coffee/hardware/arm/xarm/build_backend.py
mini_coffee/hardware/arm/xarm/core/__init__.py
mini_coffee/hardware/arm/xarm/core/comm/__init__.py
mini_coffee/hardware/arm/xarm/core/comm/base.py
mini_coffee/hardware/arm/xarm/core/comm/serial_port.py
mini_coffee/hardware/arm/xarm/core/comm/socket_port.py
mini_coffee/hardware/arm/xarm/core/comm/uxbus_cmd_protocol.py
mini_coffee/hardware/arm/xarm/core/config/__init__.py
mini_coffee/hardware/arm/xarm/core/config/x_code.py
mini_coffee/hardware/arm/xarm/core/config/x_config.py
mini_coffee/hardware/arm/xarm/core/utils/__init__.py
mini_coffee/hardware/arm/xarm/core/utils/convert.py
mini_coffee/hardware/arm/xarm/core/utils/crc16.py
mini_coffee/hardware/arm/xarm/core/utils/debug_print.py
mini_coffee/hardware/arm/xarm/core/utils/log.py
mini_coffee/hardware/arm/xarm/core/version.py
mini_coffee/hardware/arm/xarm/core/wrapper/__init__.py
mini_coffee/hardware/arm/xarm/core/wrapper/uxbus_cmd.py
mini_coffee/hardware/arm/xarm/core/wrapper/uxbus_cmd_ser.py
mini_coffee/hardware/arm/xarm/core/wrapper/uxbus_cmd_tcp.py
mini_coffee/hardware/arm/xarm/tools/__init__.py
mini_coffee/hardware/arm/xarm/tools/blockly/__init__.py
mini_coffee/hardware/arm/xarm/tools/blockly/_blockly_base.py
mini_coffee/hardware/arm/xarm/tools/blockly/_blockly_handler.py
mini_coffee/hardware/arm/xarm/tools/blockly/_blockly_highlight.py
mini_coffee/hardware/arm/xarm/tools/blockly/_blockly_node.py
mini_coffee-0.1.0.dist-info/METADATA
mini_coffee-0.1.0.dist-info/WHEEL
mini_coffee-0.1.0.dist-info/entry_points.txt
mini_coffee-0.1.0.dist-info/RECORD
