Metadata-Version: 2.3
Name: mini-coffee
Version: 0.1.0
Summary: 
Author: nemkov
Author-email: mindrobots.nemkov@gmail.com
Requires-Python: >=3.10,<3.14
Classifier: Programming Language :: Python :: 3
Classifier: Programming Language :: Python :: 3.10
Classifier: Programming Language :: Python :: 3.11
Classifier: Programming Language :: Python :: 3.12
Classifier: Programming Language :: Python :: 3.13
Requires-Dist: dotenv (>=0.9.9,<0.10.0)
Requires-Dist: pyside6 (>=6.9.0,<7.0.0)
